encryptAgit.py
encryptAgit-0.1.0.dist-info/LICENSE
encryptAgit-0.1.0.dist-info/METADATA
encryptAgit-0.1.0.dist-info/WHEEL
encryptAgit-0.1.0.dist-info/entry_points.txt
encryptAgit-0.1.0.dist-info/top_level.txt
encryptAgit-0.1.0.dist-info/RECORD
