Metadata-Version: 2.1
Name: encryptAgit
Version: 0.1.0
Summary: Encrypt your git repo
Home-page: https://github.com/secretsquirrel/encryptAgit
Author: Josh Pitts https://twitter.com/ausernamedjosh
Author-email: the.midnite.runr@gmail.com
License: UNKNOWN
Project-URL: Bug Tracker, https://github.com/secretsquirrel/encryptAgit/issues
Platform: UNKNOWN
Classifier: Programming Language :: Python :: 3
Classifier: License :: OSI Approved :: MIT License
Classifier: Operating System :: OS Independent
Requires-Python: >=3.7
License-File: LICENSE
Requires-Dist: pathspec
Requires-Dist: GitPython
Requires-Dist: cryptography
